agent_office/__init__.py
agent_office/client.py
agent_office/exceptions.py
agent_office/apis/__init__.py
agent_office/apis/base.py
agent_office/apis/documents.py
agent_office/apis/edits.py
agent_office/apis/markdown.py
agent_office/models/__init__.py
agent_office/models/document.py
agent_office/models/edit.py
agent_office/models/markdown.py
agent_office-0.0.4.dist-info/METADATA
agent_office-0.0.4.dist-info/WHEEL
agent_office-0.0.4.dist-info/top_level.txt
agent_office-0.0.4.dist-info/RECORD
