Metadata-Version: 2.4
Name: agent-office
Version: 0.0.4
Summary: Python SDK for Agent Office API - AI-powered document editing
Author-email: Agent Office <support@agentoffice.dev>
License: MIT
Project-URL: Homepage, https://agentoffice.dev
Project-URL: Documentation, https://docs.agentoffice.dev
Project-URL: Repository, https://github.com/agentoffice/python-sdk
Keywords: agent-office,api,sdk,ai,document-editing,automation
Classifier: Development Status :: 3 - Alpha
Classifier: Intended Audience :: Developers
Classifier: License :: OSI Approved :: MIT License
Classifier: Programming Language :: Python :: 3
Classifier: Programming Language :: Python :: 3.8
Classifier: Programming Language :: Python :: 3.9
Classifier: Programming Language :: Python :: 3.10
Classifier: Programming Language :: Python :: 3.11
Classifier: Programming Language :: Python :: 3.12
Requires-Python: >=3.8
Requires-Dist: requests>=2.28.0
Provides-Extra: dev
Requires-Dist: pytest>=7.0.0; extra == "dev"
Requires-Dist: black>=22.0.0; extra == "dev"
Requires-Dist: mypy>=0.990; extra == "dev"
Requires-Dist: types-requests; extra == "dev"
